pyBittle/__init__.py
pyBittle/bittleManager.py
pyBittle/bluetoothManager.py
pyBittle/serialManager.py
pyBittle/wifiManager.py
pyBittle-1.1.3.dist-info/LICENSE
pyBittle-1.1.3.dist-info/METADATA
pyBittle-1.1.3.dist-info/WHEEL
pyBittle-1.1.3.dist-info/top_level.txt
pyBittle-1.1.3.dist-info/RECORD
