Metadata-Version: 2.1
Name: pyBittle
Version: 1.1.3
Summary: Open source library for connecting and controlling Bittle.
Home-page: https://github.com/EnriqueMoran/pyBittle
Author: EnriqueMoran
Author-email: enriquemoran95@gmail.com
License: UNKNOWN
Platform: UNKNOWN
Requires-Dist: pybluez
Requires-Dist: pyserial
Requires-Dist: requests
